vrpc/VrpcLocal.py
vrpc/__init__.py
vrpc/json.hpp
vrpc/module.cpp
vrpc/vrpc.hpp
vrpc-2.4.0.dist-info/DESCRIPTION.rst
vrpc-2.4.0.dist-info/METADATA
vrpc-2.4.0.dist-info/RECORD
vrpc-2.4.0.dist-info/WHEEL
vrpc-2.4.0.dist-info/metadata.json
vrpc-2.4.0.dist-info/top_level.txt
