Metadata-Version: 2.0
Name: vrpc
Version: 2.4.0
Summary: Variadic Remote Procedure Calls
Home-page: UNKNOWN
Author: Burkhard C. Heisen
Author-email: burkhard.heisen@heisenware.com
License: MIT
Keywords: c++-to-python,language-bindings,iot,rpc,bindings,c++14,bindings-generator,remote-procedure-call
Platform: UNKNOWN
Classifier: Programming Language :: Python :: 3
Requires-Python: >=3
